awsserviceendpoints/__init__.py
awsserviceendpoints/data/endpoints.json
awsserviceendpoints-0.0.2.dist-info/LICENSE
awsserviceendpoints-0.0.2.dist-info/METADATA
awsserviceendpoints-0.0.2.dist-info/WHEEL
awsserviceendpoints-0.0.2.dist-info/top_level.txt
awsserviceendpoints-0.0.2.dist-info/RECORD
