Metadata-Version: 2.1
Name: awsserviceendpoints
Version: 0.0.2
Summary: Micropackage that changes boto3 to return the standard service endpoints
Home-page: UNKNOWN
Author: Joseph Wortmann
Author-email: jwortmann@quinovas.com
License: UNKNOWN
Platform: UNKNOWN
License-File: LICENSE
